cite2c/__init__.py
cite2c/handlers.py
cite2c/install.py
cite2c/oauth_success.html
cite2c/zotero_oauth.py
cite2c/nbext/chicago-author-date.csl
cite2c/nbext/chicago-fullnote-bibliography.csl
cite2c/nbext/citeproc.js
cite2c/nbext/main.js
cite2c/nbext/rendering.js
cite2c/nbext/styles.css
cite2c/nbext/typeahead.bundle.min.js
cite2c/nbext/typeahead.jquery.js
cite2c/nbext/xmldom.js
cite2c-0.2.1.dist-info/LICENSE
cite2c-0.2.1.dist-info/WHEEL
cite2c-0.2.1.dist-info/METADATA
cite2c-0.2.1.dist-info/RECORD
