Metadata-Version: 1.2
Name: cite2c
Version: 0.2.1
Summary: Citations for Jupyter Notebooks
Home-page: https://github.com/takluyver/cite2c
License: UNKNOWN
Author: Thomas Kluyver
Author-email: thomas@kluyver.me.uk
Classifier: License :: OSI Approved :: MIT License
Requires-Dist: notebook
Requires-Dist: tornado
Requires-Dist: rauth
